NeuroUtils/Architectures.py
NeuroUtils/Core.py
NeuroUtils/ML_assets.py
NeuroUtils/__init__.py
NeuroUtils/Assets/Background.png
NeuroUtils-0.2.3.dist-info/LICENSE.txt
NeuroUtils-0.2.3.dist-info/METADATA
NeuroUtils-0.2.3.dist-info/WHEEL
NeuroUtils-0.2.3.dist-info/top_level.txt
NeuroUtils-0.2.3.dist-info/RECORD
